{"Title": "Analysis of Public Opinion on Public Transportation in Bandung and Jakarta in Twitter using Indonesian Bidirectional Encoder Representations from Transformer", "Doi": "10.1109/IAICT59002.2023.10205608", "Authors": ["d. pratama", "s. akbar"], "Key Words": ["sentiment analysis", "social media mining", "twitter", "deep learning", "indobert"], "Abstract": "transportation has been one of the main challenges for people living in urban areas especially in big cities. handling transportation problems traditionally is no longer considered suitable due to the increasingly large and complex data which calls for an intelligent transportation system. one source of data that can be used to is social media  twitter  in which the development of user generated content can improve the management of existing transportation systems. in this study indobert as a state of the art model in natural language processing tasks is used to perform sentiment analysis on indonesian tweets about public transportation to have a better understanding of tweet context. experimental results show that indobert performs better than traditional machine learning algorithm with the best combination of hyperparameter tuning results in accuracy of 94.8% which generalizes best to the dataset.", "Pub Date": "2023-08-09"}