{"Title": "Blockchain-Empowered Secure Aerial Edge Computing for AIoT Devices", "Doi": "10.1109/JIOT.2023.3294222", "Authors": ["z. zhang", "k. zeng", "y. yi"], "Key Words": ["artificial intelligence of things (aiot)", "blockchain", "computation offloading", "mobile-edge computing (mec)", "unmanned aerial vehicle (uav)"], "Abstract": "the unmanned aerial vehicle  uav  equipped with mobile edge computing  mec  can act as an air base station to provide computing services for artificial intelligence of things  aiot  devices in remote areas. however the computation offloading process poses a risk to users\u201a\u00e4\u00f4 privacy due to potential information leaks resulting from interactions between uavs or migration of data between aiot devices and uavs. in this article we proposed a secure aerial computing network that integrates mec and blockchain technologies to effectively guarantee privacy and security during computation offloading between aiot devices and uavs. additionally taking into account task offloading scheduling radio spectrum resource allocation and computation resource allocation a joint optimization problem is formulated to minimize the weighted sum of delay and energy consumption throughout the entire computing process. to tackle this issue we proposed a block coordinate descent  bcd  based algorithm to solve the mixed integer and nonconvex problem. simulation results demonstrate that the proposed algorithm surpasses other baseline approaches.", "Pub Date": "2023-12-27"}