{"Title": "Energy Consumption and QoS-Aware Co-Offloading for Vehicular Edge Computing", "Doi": "10.1109/JIOT.2022.3221966", "Authors": ["w. lv", "p. yang", "t. zheng", "b. yi", "y. ding", "q. wang", "m. deng"], "Key Words": ["bayesian optimization (bo)", "computation offloading", "energy consumption", "quality of service (qos)", "vehicular edge computing (vec)"], "Abstract": "by deploying computing storage and bandwidth resources at the user side vehicular edge computing  vec  provides low delay services for vehicle users. however due to the limited resources of edge servers how to efficiently meet the quality of service  qos  requirements of multiple tasks and save the total energy consumption in a dynamic environment is an important issue in vec. in this article we first propose an energy consumption and qos aware co offloading model. unlike most previous studies our goal is to minimize the total energy consumption while guaranteeing the qos constraints of tasks thus avoiding the overallocation of resources and high energy consumption caused by the one sided pursuit of delay minimization. then without the requirements for domain experts we propose bayesian optimization based computation offloading  boco  method to find the optimal offloading decision. to the best of our knowledge this work is the first to apply bayesian optimization to computation offloading in vec. furthermore we conduct a series of experiments and comparisons with other offloading methods to analyze the effectiveness and performance of the proposed algorithm. experimental results verify that our proposed boco outperforms counterparts.", "Pub Date": "2023-03-07"}