{"Title": "Features and Potentialities of Static Passive EM Skins for NLOS Specular Wireless Links", "Authors": ["g. oliveri", "m. salucci", "a. massa"], "Pub Date": "2023-10-05", "Abstract": "the ability of passive flat patterned electromagnetic skins  emss  to overcome the asymptotic limit of the total path attenuation  tpa  of flat metallic reflectors in non line of sight  nlos  specular point to point fixed wireless access applications is assessed. for the first time to the best of the authors\u201a\u00e4\u00f4 knowledge closed form expressions of the achievable tpa in ems powered nlos links are stated. the condition on the panel size of ems screens to overcome the performance of flat passive conductive screens  pcss  with the same aperture is derived and numerically validated.", "Doi": "10.1109/TAP.2023.3301654", "Key Words": ["access", "fixed wireless", "inverse problems", "inverse scattering", "metamaterials", "next-generation communications", "point-to-point wireless link", "smart electromagnetic environment (seme)", "static passive em skins"]}