{"Title": "Intelligent Content Caching and User Association in Mobile Edge Computing Networks for Smart Cities", "Doi": "10.1109/TNSE.2023.3312369", "Authors": ["h. li", "x. li", "c. sun", "f. fang", "q. fan", "x. wang", "v. c. m. leung"], "Key Words": ["mobile edge computing networks", "content caching", "user association", "weighted latent factor model"], "Abstract": "to support rapidly increasing multimedia services of smart cities mobile edge computing  mec  networks can significantly reduce content acquisition latency. however due to user mobility and the possibility of re association it is challenging to obtain a proper content caching and user association policy. in this article we investigate the issue of joint content caching and user association with high user mobility in mec networks by minimizing content acquisition latency and handover latency. to address the problem we optimize the original mixed time scale problem in two stages  long time scale content caching and short time scale user association. we propose an intelligent content caching framework based on a weighted latent factor model to determine content caching policy at each time frame. then we design a matching theory based lazy re association strategy at each time slot. simulation results on real world mec networks demonstrate the effectiveness of the proposed framework.", "Pub Date": "2024-01-05"}