{"Title": "Joint mmWave Beamforming and Resource Allocation in NOMA-MEC Network for Internet of Things", "Doi": "10.1109/TVT.2022.3229078", "Authors": ["x. qi", "m. peng", "h. zhang"], "Key Words": ["hybrid beamforming", "massive mimo", "mobile edge computing", "noma", "resource allocation"], "Abstract": "mobile edge computing  mec  technology can reduce the computational burden of internet of things  iot  devices by offloading computationally intensive tasks to physically proximate edge servers. the combination of millimeter wave  mmwave  massive multiple input multiple output  mimo  and non orthogonal multiple access  noma  technique has draw significant attention for its high spectral efficiency. this paper merges the computation offloading and mmwave massive mimo noma communication to seek energy efficient performance for iot devices in mec network. first we propose an iot device clustering algorithm to schedule all iot devices into limited beams. following this we minimize the total energy consumption of computing and offloading in the noma mec network by jointly optimizing hybrid beamforming offloading task assignment  ota  ratio and power allocation. then the non convex joint optimization problem is solved by proposing a suboptimal solution with two stages. in the first stage a cyclic block coordinate update algorithm is proposed for analog beamforming design and then the digital beamforming vectors are obtained by zero forcing method. in the second stage an alternating minimization algorithm is proposed to optimize the ota ratio and power allocation. finally simulation results are provided to validate the convergence of the proposed algorithms and the superiority of our proposed schemes over other benchmark schemes which demonstrate the outstanding performance leveraging the massive mimo noma technique during computational offloading.", "Pub Date": "2023-04-18"}