{"Title": "Syntax and Domain Aware Model for Unsupervised Program Translation", "Doi": "10.1109/ICSE48619.2023.00072", "Authors": ["f. liu", "j. li", "l. zhang"], "Key Words": ["program translation", "neural networks", "syntax structure", "unsupervised learning"], "Abstract": "there is growing interest in software migration as the development of software and society. manually migrating projects between languages is error prone and expensive. in recent years researchers have begun to explore automatic program translation using supervised deep learning techniques by learning from large scale parallel code corpus. however parallel resources are scarce in the programming language domain and it is costly to collect bilingual data manually. to address this issue several unsupervised programming translation systems are proposed. however these systems still rely on huge monolingual source code to train which is very expensive. besides these models cannot perform well for translating the languages that are not seen during the pre training procedure. in this paper we propose sda trans a syntax and domain aware model for program translation which leverages the syntax structure and domain knowledge to enhance the cross lingual transfer ability. sda trans adopts unsupervised training on a smaller scale corpus including python and java monolingual programs. the experimental results on function translation tasks between python java and c++ show that sda trans outperforms many large scale pre trained models especially for unseen language translation.", "Pub Date": "2023-07-14"}