{"Title": "Task Offloading and Resource Allocation Strategies Among Multiple Edge Servers", "Doi": "10.1109/JIOT.2023.3343793", "Authors": ["b. shi", "y. wu"], "Key Words": ["deep reinforcement learning", "mobile-edge computing", "partially observable markov game (pomg)", "resource allocation", "task offloading"], "Abstract": "mobile edge computing has been widely used in the internet of things  iot  field. in mobile edge computing users\u201a\u00e4\u00f4 tasks can be executed on local devices or offloaded to edge servers for processing. however in the multiedge server collaboration scenario service coverage of multiple edge servers may overlap with each other. therefore users in the overlapped service coverage areas need to determine which server to be offloaded. inefficient task offloading strategies may result in unbalanced workloads of the edge servers which causes negative impacts on task completion latency and the total number of served users. to address this problem we propose a task offloading and resource allocation strategy in a multiedge server collaboration scenario in this article. in more detail we consider that task demands arrive dynamically and tasks can be processed locally or offloaded to edge servers. we then model the task offloading and resource allocation problem as a partially observable markov game  pomg  and propose a task offloading and resource allocation strategy based on a reinforcement learning algorithm i pdqn to ensure that the task latency requirements are met while maximizing the number of served users and minimizing the average task energy consumption. finally we evaluate the performance of the strategy proposed in this article against some typical benchmark strategies under different system parameters through experiments. the experimental results show that the i pdqn based task offloading and resource allocation strategy can outperform benchmark approaches.", "Pub Date": "2024-04-09"}