{"Title": "Towards an Efficient SIMD Virtual Radio Access Network (vRAN) and Edge Cloud System", "Doi": "10.1109/TCC.2023.3275576", "Authors": ["j. wang", "z. wang", "y. hu"], "Key Words": ["mobile edge computing", "radio access network", "micro-architecture", "mobile edge co-located workloads"], "Abstract": "nowadays virtual radio access network  vran  plays a vital role in today mobile edge system for its better support for latency sensitive applications. however our characterization of vran on modern processors depicts a frustrating picture of single instruction multi data  simd  acceleration. specifically the existing data arrangement processes cannot efficiently utilize the ports in modern processors which leads to high backend bound and fails to saturate the memory bandwidth between registers and the l1 cache. to tackle the issue we thoroughly examine the state of the art cpu architecture and observe the idle ports which could be utilized by the process. motivated by this observation we propose an \u201a\u00e4\u00faarithmetic ports consciousness mechanism\u201a\u00e4\u00f9  apcm  utilizing these idle ports to eliminate the backend bound and saturate the memory bandwidth. the apcm decreases the data arrangement backend bound from 45$\\%$% to 3$\\%$% and promotes its memory bandwidth utilization by 4x 16x. moreover we illustrate that the apcm can be utilized to promote the performance of typical mobile edge applications such as network routing image processing and artificial intelliegence applications. the cpu time of the data arrangement process time of the selected typical mobile edge applications can be reduced by 55$\\%$%   95$\\%$% when utilizing the proposed mechanism.", "Pub Date": "2023-09-05"}